cjm_pytorch_utils/__init__.py
cjm_pytorch_utils/_modidx.py
cjm_pytorch_utils/core.py
cjm_pytorch_utils/pytorch_utils.py
cjm_pytorch_utils-0.0.8.dist-info/LICENSE
cjm_pytorch_utils-0.0.8.dist-info/METADATA
cjm_pytorch_utils-0.0.8.dist-info/WHEEL
cjm_pytorch_utils-0.0.8.dist-info/entry_points.txt
cjm_pytorch_utils-0.0.8.dist-info/top_level.txt
cjm_pytorch_utils-0.0.8.dist-info/RECORD
