Metadata-Version: 2.1
Name: cjm-pytorch-utils
Version: 0.0.8
Summary: Some utility functions for working with PyTorch.
Home-page: https://github.com/cj-mills/cjm-pytorch-utils
Author: cj-mills
Author-email: millscj.mills2@gmail.com
License: Apache Software License 2.0
Keywords: nbdev jupyter notebook python
Classifier: Development Status :: 4 - Beta
Classifier: Intended Audience :: Developers
Classifier: Natural Language :: English
Classifier: Programming Language :: Python :: 3.9
Classifier: Programming Language :: Python :: 3.10
Classifier: License :: OSI Approved :: Apache Software License
Requires-Python: >=3.9
License-File: LICENSE
Requires-Dist: pandas
Requires-Dist: numpy
Requires-Dist: torch
Requires-Dist: torchvision
Requires-Dist: pillow
Requires-Dist: tqdm
Provides-Extra: dev
